check50/__init__.py
check50/__main__.py
check50/_api.py
check50/_exceptions.py
check50/_simple.py
check50/c.py
check50/contextmanagers.py
check50/flask.py
check50/internal.py
check50/py.py
check50/regex.py
check50/runner.py
check50/renderer/__init__.py
check50/renderer/_renderers.py
check50/renderer/templates/results.html
check50-3.3.11.dist-info/LICENSE
check50-3.3.11.dist-info/METADATA
check50-3.3.11.dist-info/WHEEL
check50-3.3.11.dist-info/entry_points.txt
check50-3.3.11.dist-info/top_level.txt
check50-3.3.11.dist-info/RECORD
